mcmm/__init__.py
mcmm/model.py
pymcmm-0.3.1.dist-info/licenses/LICENSE
pymcmm-0.3.1.dist-info/METADATA
pymcmm-0.3.1.dist-info/WHEEL
pymcmm-0.3.1.dist-info/top_level.txt
pymcmm-0.3.1.dist-info/RECORD
