Metadata-Version: 2.4
Name: pymcmm
Version: 0.3.1
Summary: Mixed-Copula Mixture Model for clustering mixed-type data
Home-page: https://github.com/YuZhao20/pymcmm
Author: Yu Zhao
License: MIT
Project-URL: Homepage, https://github.com/YuZhao20/pymcmm
Project-URL: Documentation, https://github.com/YuZhao20/pymcmm#readme
Project-URL: Repository, https://github.com/YuZhao20/pymcmm
Project-URL: Issues, https://github.com/YuZhao20/pymcmm/issues
Keywords: clustering,mixture-model,copula,mixed-data,machine-learning
Classifier: Development Status :: 4 - Beta
Classifier: Intended Audience :: Science/Research
Classifier: License :: OSI Approved :: MIT License
Classifier: Programming Language :: Python :: 3
Classifier: Programming Language :: Python :: 3.8
Classifier: Programming Language :: Python :: 3.9
Classifier: Programming Language :: Python :: 3.10
Classifier: Programming Language :: Python :: 3.11
Classifier: Programming Language :: Python :: 3.12
Classifier: Topic :: Scientific/Engineering :: Artificial Intelligence
Requires-Python: >=3.8
License-File: LICENSE
Requires-Dist: numpy>=1.20
Requires-Dist: pandas>=1.3
Requires-Dist: scipy>=1.7
Requires-Dist: scikit-learn>=1.0
Requires-Dist: joblib>=1.0
Provides-Extra: dev
Requires-Dist: cython>=0.29; extra == "dev"
Requires-Dist: pytest>=6.0; extra == "dev"
Requires-Dist: pytest-cov>=2.0; extra == "dev"
Provides-Extra: cython
Requires-Dist: cython>=0.29; extra == "cython"
Dynamic: home-page
Dynamic: license-file
Dynamic: requires-python
